<retConsReciNFe xmlns="http://www.portalfiscal.inf.br/nfe" versao="3.10"><tpAmb>2</tpAmb><verAplic>AM3.10</verAplic><nRec>130000017318956</nRec><cStat>104</cStat><xMotivo>Lote processado</xMotivo><cUF>13</cUF><dhRecbto>2015-10-22T17:11:44-04:00</dhRecbto><protNFe versao="3.10"><infProt><tpAmb>2</tpAmb><verAplic>AM3.10</verAplic><chNFe>13151019570121000105550010000002301000002303</chNFe><dhRecbto>2015-10-22T17:11:44-04:00</dhRecbto><cStat>732</cStat><xMotivo>Rejeicao: CFOP de operacao interestadual e idDest diferente de 2</xMotivo></infProt></protNFe></retConsReciNFe>
